{
  "core_systems": {
    "autonomous_agents": "Self-replicating agents for all industries",
    "swarm_intelligence": "Hivemind coordination with consensus",
    "knowledge_base": "Recursive knowledge growth system",
    "mcp_integration": "109 tools across 6 connectors",
    "zapier_automation": "18 workflows for all industries"
  },
  "infrastructure": {
    "eks_cluster": "true-asi-cluster configuration",
    "s3_storage": "Data persistence layer",
    "ec2_compute": "Processing nodes",
    "lambda_functions": "Serverless operations"
  },
  "data_layers": {
    "agents": "1.18M agent files",
    "knowledge": "Knowledge graph and embeddings",
    "models": "AI model configurations",
    "processing": "Data processing pipelines"
  },
  "scale_targets": {
    "agents": 1000000,
    "knowledge_nodes": 10000000,
    "connections": 100000000
  }
}